linkhub/__init__.py
linkhub/linkhub.py
linkhub-1.6.0.dist-info/LICENSE.md
linkhub-1.6.0.dist-info/METADATA
linkhub-1.6.0.dist-info/WHEEL
linkhub-1.6.0.dist-info/top_level.txt
linkhub-1.6.0.dist-info/RECORD
