Metadata-Version: 2.1
Name: linkhub
Version: 1.6.0
Summary: Linkhub Auth Library
Home-page: https://github.com/linkhub-sdk/Linkhub.py
Author: Kim Seongjun
Author-email: pallet027@gmail.com
License: MIT
Download-URL: https://github.com/linkhub-sdk/linkhub.py/archive/1.6.0.tar.gz
Platform: Posix; MacOS X; Windows
Classifier: Development Status :: 5 - Production/Stable
Classifier: Intended Audience :: Developers
Classifier: License :: OSI Approved :: MIT License
Classifier: Operating System :: OS Independent
Classifier: Topic :: Internet
Classifier: Programming Language :: Python :: 2
Classifier: Programming Language :: Python :: 2.6
Classifier: Programming Language :: Python :: 2.7
Classifier: Programming Language :: Python :: 3
Classifier: Programming Language :: Python :: 3.3
Classifier: Programming Language :: Python :: 3.4
